cparo/__init__.py
cparo/paro.py
cparo-2.1.dist-info/METADATA
cparo-2.1.dist-info/WHEEL
cparo-2.1.dist-info/entry_points.txt
cparo-2.1.dist-info/top_level.txt
cparo-2.1.dist-info/RECORD
