Metadata-Version: 2.1
Name: cparo
Version: 2.1
Requires-Dist: requests
Requires-Dist: pyperclip
